Changelog.rst
Developer_Manual.rst
LICENSE.txt
MANIFEST.in
README.rst
pyproject.toml
setup.py
Nuitka.egg-info/PKG-INFO
Nuitka.egg-info/SOURCES.txt
Nuitka.egg-info/dependency_links.txt
Nuitka.egg-info/entry_points.txt
Nuitka.egg-info/not-zip-safe
Nuitka.egg-info/requires.txt
Nuitka.egg-info/top_level.txt
bin/autoformat-nuitka-source
bin/check-nuitka-with-pylint
bin/compare_with_cpython
bin/compare_with_xml
bin/measure-construct-performance
bin/nuitka
bin/nuitka-run
doc/nuitka-run.1
doc/nuitka.1
doc/Logo/Nuitka-Logo-Horizontal.svg
doc/Logo/Nuitka-Logo-Symbol.svg
doc/Logo/Nuitka-Logo-Vertical.svg
doc/images/Nuitka-Logo-Horizontal.png
doc/images/Nuitka-Logo-Symbol.png
doc/images/Nuitka-Logo-Vertical.png
lib/hints.py
misc/nuitka-run.cmd
misc/nuitka.cmd
nuitka/Builtins.py
nuitka/BytecodeCaching.py
nuitka/Bytecodes.py
nuitka/CacheCleanup.py
nuitka/Constants.py
nuitka/Errors.py
nuitka/HardImportRegistry.py
nuitka/MainControl.py
nuitka/ModuleRegistry.py
nuitka/OptionParsing.py
nuitka/Options.py
nuitka/OutputDirectories.py
nuitka/PostProcessing.py
nuitka/Progress.py
nuitka/PythonFlavors.py
nuitka/PythonOperators.py
nuitka/PythonVersions.py
nuitka/Serialization.py
nuitka/SourceCodeReferences.py
nuitka/Tracing.py
nuitka/TreeXML.py
nuitka/Variables.py
nuitka/Version.py
nuitka/__init__.py
nuitka/__main__.py
nuitka/__past__.py
nuitka/build/Backend.scons
nuitka/build/CCompilerVersion.scons
nuitka/build/DataComposerInterface.py
nuitka/build/Offsets.scons
nuitka/build/Onefile.scons
nuitka/build/SconsCaching.py
nuitka/build/SconsCompilerSettings.py
nuitka/build/SconsHacks.py
nuitka/build/SconsInterface.py
nuitka/build/SconsProgress.py
nuitka/build/SconsPythonBuild.py
nuitka/build/SconsSpawn.py
nuitka/build/SconsUtils.py
nuitka/build/__init__.py
nuitka/build/include/nuitka/allocator.h
nuitka/build/include/nuitka/builtins.h
nuitka/build/include/nuitka/calling.h
nuitka/build/include/nuitka/checkers.h
nuitka/build/include/nuitka/checksum_tools.h
nuitka/build/include/nuitka/compiled_asyncgen.h
nuitka/build/include/nuitka/compiled_cell.h
nuitka/build/include/nuitka/compiled_coroutine.h
nuitka/build/include/nuitka/compiled_frame.h
nuitka/build/include/nuitka/compiled_function.h
